MANIFEST.in
README.md
setup.py
examples/bayes_example.py
examples/bp_network_example.py
examples/cervical_cancer.py
examples/cluster_example.py
examples/ensemble_example.py
examples/feature_select_eaxmple.py
examples/knn_example.py
examples/logistic_example.py
examples/multi_regression_example.py
examples/optimal_example.py
examples/pca_example.py
examples/risk_factors_cervical_cancer.csv
examples/stacking_example.py
examples/support_vector_eaxmple.py
examples/svm_example.py
examples/tree_example.py
simple_male.egg-info/PKG-INFO
simple_male.egg-info/SOURCES.txt
simple_male.egg-info/dependency_links.txt
simple_male.egg-info/requires.txt
simple_male.egg-info/top_level.txt
simple_ml/__init__.py
simple_ml/auto.py
simple_ml/bayes.py
simple_ml/classify_data.py
simple_ml/cluster.py
simple_ml/data_handle.py
simple_ml/ensemble.py
simple_ml/evaluation.py
simple_ml/feature_select.py
simple_ml/helper.py
simple_ml/knn.py
simple_ml/logistic.py
simple_ml/neural_network.py
simple_ml/optimal.py
simple_ml/pca.py
simple_ml/regression.py
simple_ml/support_vector.py
simple_ml/svm.py
simple_ml/tree.py
simple_ml/base/__init__.py
simple_ml/base/base_enum.py
simple_ml/base/base_error.py
simple_ml/base/base_model.py
simple_ml/data_sets/__init__.py
simple_ml/data_sets/circle_200.txt
simple_ml/data_sets/hastie_10_2.txt
simple_ml/data_sets/iris.txt
simple_ml/data_sets/moon_200.txt
simple_ml/data_sets/watermelon.txt
simple_ml/data_sets/wine.txt
simple_ml/data_sets/download/adult.data
simple_ml/data_sets/download/iris.data