Metadata-Version: 1.1
Name: simple-male
Version: 0.1.2
Summary: A machine learning algorithm implementation
Home-page: https://yangruipis.github.io/simple_ml/
Author: Ray Yang
Author-email: yangruipis@163.com
License: MIT
Platform: UNKNOWN
Classifier: Environment :: Console
Classifier: Intended Audience :: End Users/Desktop
Classifier: License :: OSI Approved :: MIT License
Classifier: Operating System :: Microsoft
Classifier: Operating System :: POSIX
Classifier: Programming Language :: Python :: 3.5
Classifier: Programming Language :: Python :: 3.6
